dynflatfield/totalvar.c
dynflatfield/correction.py
dynflatfield/batch_processor.py
dynflatfield/totalvar_numba.py
dynflatfield/constants.py
dynflatfield/__init__.py
dynflatfield/_version.py
dynflatfield/totalvar_cython.cpython-310-x86_64-linux-gnu.so
dynflatfield/ctotalvar.pyx
dynflatfield/draw.py
dynflatfield/parallel/mpfarm.py
dynflatfield/parallel/shmem.py
dynflatfield/parallel/__init__.py
dynflatfield/parallel/image_reader.py
dynflatfield-1.1.0.dist-info/top_level.txt
dynflatfield-1.1.0.dist-info/RECORD
dynflatfield-1.1.0.dist-info/LICENSE
dynflatfield-1.1.0.dist-info/METADATA
dynflatfield-1.1.0.dist-info/WHEEL
